srcview.py
srcview-0.1.1.dist-info/METADATA
srcview-0.1.1.dist-info/WHEEL
srcview-0.1.1.dist-info/RECORD
